pyproject.toml
readme.md
bincsync/__init__.py
bincsync/ansi.py
bincsync/fetch.py
bincsync/make.py
bincsync/push.py
bincsync/utils.py
bincsync.egg-info/PKG-INFO
bincsync.egg-info/SOURCES.txt
bincsync.egg-info/dependency_links.txt
bincsync.egg-info/entry_points.txt
bincsync.egg-info/requires.txt
bincsync.egg-info/top_level.txt