Metadata-Version: 2.4
Name: bincsync
Version: 0.2.0
Summary: bincsync: Binary incremental sync
Author-email: Zheng Yang <xornent@outlook.com>
Project-URL: Repository, https://github.com/yang-z-03/bincsync
Requires-Python: <3.13,>=3.9
Requires-Dist: bsdiff4
Requires-Dist: oss2
Requires-Dist: pandas
Provides-Extra: dev
Requires-Dist: sphinx; extra == "dev"
Requires-Dist: sphinx-rtd-theme; extra == "dev"
Requires-Dist: twine; extra == "dev"
Requires-Dist: ipykernel; extra == "dev"
